resonitelink/__init__.py
resonitelink/client.py
resonitelink/exceptions/__init__.py
resonitelink/exceptions/resonitelink_exceptions.py
resonitelink/json/__init__.py
resonitelink/json/decoder.py
resonitelink/json/encoder.py
resonitelink/json/models.py
resonitelink/json/utils.py
resonitelink/logging/__init__.py
resonitelink/logging/logging.py
resonitelink/models/assets/mesh/__init__.py
resonitelink/models/assets/mesh/bone.py
resonitelink/models/assets/mesh/json/__init__.py
resonitelink/models/assets/mesh/json/blendshape.py
resonitelink/models/assets/mesh/json/blendshape_frame.py
resonitelink/models/assets/mesh/json/bone_weight.py
resonitelink/models/assets/mesh/json/point_submesh.py
resonitelink/models/assets/mesh/json/submesh.py
resonitelink/models/assets/mesh/json/triangle.py
resonitelink/models/assets/mesh/json/triangle_submesh.py
resonitelink/models/assets/mesh/json/uv_coordinate.py
resonitelink/models/assets/mesh/json/vertex.py
resonitelink/models/assets/mesh/raw_data/__init__.py
resonitelink/models/assets/mesh/raw_data/blendshape_frame_raw_data.py
resonitelink/models/assets/mesh/raw_data/blendshape_raw_data.py
resonitelink/models/assets/mesh/raw_data/bone_weight_raw_data.py
resonitelink/models/assets/mesh/raw_data/point_submesh_raw_data.py
resonitelink/models/assets/mesh/raw_data/submesh_raw_data.py
resonitelink/models/assets/mesh/raw_data/triangle_submesh_raw_data.py
resonitelink/models/datamodel/__init__.py
resonitelink/models/datamodel/field.py
resonitelink/models/datamodel/member.py
resonitelink/models/datamodel/sync_array.py
resonitelink/models/datamodel/sync_list.py
resonitelink/models/datamodel/sync_object.py
resonitelink/models/datamodel/worker.py
resonitelink/models/datamodel/members/__init__.py
resonitelink/models/datamodel/members/empty_element.py
resonitelink/models/datamodel/members/field_enum.py
resonitelink/models/datamodel/members/reference.py
resonitelink/models/datamodel/primitives/__init__.py
resonitelink/models/datamodel/primitives/colors.py
resonitelink_py-0.1.0b77.dist-info/licenses/LICENSE
resonitelink_py-0.1.0b77.dist-info/METADATA
resonitelink_py-0.1.0b77.dist-info/WHEEL
resonitelink_py-0.1.0b77.dist-info/top_level.txt
resonitelink_py-0.1.0b77.dist-info/RECORD
