Metadata-Version: 2.4
Name: resonitelink.py
Version: 0.1.0b77
Summary: A Python wrapper for the ResoniteLink API
Author: JackTheFoxOtter
License-Expression: MIT
Project-URL: Homepage, https://github.com/JackTheFoxOtter/ResoniteLink.py
Classifier: Development Status :: 3 - Alpha
Classifier: Intended Audience :: Developers
Classifier: Natural Language :: English
Classifier: Operating System :: OS Independent
Classifier: Programming Language :: Python :: 3
Classifier: Programming Language :: Python :: 3.14
Classifier: Topic :: Software Development :: Libraries
Classifier: Topic :: Software Development :: Libraries :: Python Modules
Classifier: Topic :: Utilities
Classifier: Typing :: Typed
Requires-Python: >=3.14
License-File: LICENSE
Requires-Dist: websockets==15.0.1
Dynamic: license-file
